cadworkbridge/1170.py
cadworkbridge/CltPanel_V3.py
cadworkbridge/Exceptions_V3.py
cadworkbridge/Loading_V3.py
cadworkbridge/Materials_V3.py
cadworkbridge/Units_V3.py
cadworkbridge/__init__.py
cadworkbridge-0.1.3.dist-info/licenses/LICENSE
cadworkbridge-0.1.3.dist-info/METADATA
cadworkbridge-0.1.3.dist-info/WHEEL
cadworkbridge-0.1.3.dist-info/top_level.txt
cadworkbridge-0.1.3.dist-info/RECORD
