Metadata-Version: 2.4
Name: cadworkbridge
Version: 0.1.3
Summary: Short description of your library
Author-email: Your Name <you@example.com>
License: MIT
Requires-Python: >=3.7
License-File: LICENSE
Requires-Dist: pandas
Requires-Dist: numpy
Dynamic: license-file
